affect/__init__.py
affect/exceptions.py
affect/py.typed
affect/typings.py
affect/version.py
affect/core/__init__.py
affect/core/_core.py
affect/core/_decorators.py
affect/core/_helpers.py
affect-0.1.0.dist-info/licenses/LICENSE
affect-0.1.0.dist-info/METADATA
affect-0.1.0.dist-info/WHEEL
affect-0.1.0.dist-info/top_level.txt
affect-0.1.0.dist-info/RECORD
