Metadata-Version: 2.4
Name: affect
Version: 0.1.0
Summary: Build robust python applications
License: MIT License
Project-URL: Documentation, https://matthewmckee4.github.io/affect/
Project-URL: Homepage, https://matthewmckee4.github.io/affect/
Project-URL: Issues, https://github.com/MatthewMckee4/affect/issues
Project-URL: Repository, https://github.com/MatthewMckee4/affect
Classifier: Typing :: Typed
Classifier: Programming Language :: Python :: 3.11
Classifier: Programming Language :: Python :: 3.12
Classifier: Programming Language :: Python :: 3.13
Requires-Python: >=3.11
License-File: LICENSE
Requires-Dist: pydantic>=2.10.6
Requires-Dist: pydantic-settings>=2.8.0
Provides-Extra: dev
Requires-Dist: build>=1.2.2.post1; extra == "dev"
Requires-Dist: mypy>=1.15.0; extra == "dev"
Requires-Dist: pre-commit>=4.1.0; extra == "dev"
Requires-Dist: ruff>=0.9.7; extra == "dev"
Requires-Dist: tbump>=6.11.0; extra == "dev"
Provides-Extra: docs
Requires-Dist: mkdocs; extra == "docs"
Requires-Dist: mkdocs-jupyter>=0.24; extra == "docs"
Requires-Dist: mkdocstrings[python]; extra == "docs"
Requires-Dist: mkdocs-material; extra == "docs"
Provides-Extra: test
Requires-Dist: pytest-cov>=6.0.0; extra == "test"
Requires-Dist: pytest-randomly>=3.16.0; extra == "test"
Requires-Dist: pytest-xdist>=3.6.0; extra == "test"
Requires-Dist: pytest>=8.3.5; extra == "test"
Requires-Dist: pytest-asyncio>=0.25.3; extra == "test"
Dynamic: license-file
